{
  "version": 1,
  "templates": [
    {
      "id": "forest.ru.0001",
      "text": "🌿 {user} пугал лису свистом, поскользнулся на хвое и поднял {delta} с тропы!"
    },
    {
      "id": "forest.ru.0002",
      "text": "🐿️ {user} смотрел, как мох растёт, услышал хруст в кустах и выкопал {delta} из-под коряги!"
    },
    {
      "id": "forest.ru.0003",
      "text": "🪶 {user} обходил поляну по периметру, повстречал ёжика и случайно зацепил {delta} лаптём!"
    },
    {
      "id": "forest.ru.0004",
      "text": "🦉 {user} рыл схрон под корягой, споткнулся о корни и намерил {delta} у самого пня!"
    },
    {
      "id": "forest.ru.0005",
      "text": "🐺 {user} наблюдал за белкой на сосне, перепутал тропу и увидел {delta} в траве и обрадовался!"
    },
    {
      "id": "forest.ru.0006",
      "text": "🪶 {user} выпиливал свисток из ветки, полез за грибом и услышал шёпот папоротника — и стал на {delta} длиннее!"
    },
    {
      "id": "forest.ru.0007",
      "text": "🦌 {user} переплетал лапти у пня, наткнулся на дупло и случайно зацепил {delta} лаптём!"
    },
    {
      "id": "forest.ru.0008",
      "text": "🌳 {user} рыл схрон под корягой, распугал бабочек и нашёл {delta} в густой листве!"
    },
    {
      "id": "forest.ru.0009",
      "text": "🦡 {user} переплетал лапти у пня, подобрал странный камень и услышал шёпот папоротника — и стал на {delta} длиннее!"
    },
    {
      "id": "forest.ru.0010",
      "text": "🍂 {user} разгребал муравейник палкой, решил передохнуть и поднял {delta} с тропы!"
    },
    {
      "id": "forest.ru.0011",
      "text": "🐿️ {user} плёл венок из папоротника, повстречал ёжика и обнаружил {delta} прямо в мхе!"
    },
    {
      "id": "forest.ru.0012",
      "text": "🌿 {user} пел грустные песни ёлкам, вспомнил детство и намерил {delta} у самого пня!"
    },
    {
      "id": "forest.ru.0013",
      "text": "🐗 {user} продирался сквозь чащу, решил передохнуть и вытряхнул {delta} из шапки!"
    },
    {
      "id": "forest.ru.0014",
      "text": "🍂 {user} пугал лису свистом, вспомнил детство и получил {delta} в подарок от лешего!"
    },
    {
      "id": "forest.ru.0015",
      "text": "🌿 {user} точил топор о валун, поскользнулся на хвое и выторговал {delta} у лесного духа!"
    },
    {
      "id": "forest.ru.0016",
      "text": "🪶 {user} ловил эхо у скалы, наткнулся на дупло и услышал шёпот папоротника — и стал на {delta} длиннее!"
    },
    {
      "id": "forest.ru.0017",
      "text": "🪵 {user} точил топор о валун, подобрал странный камень и получил {delta} в подарок от лешего!"
    },
    {
      "id": "forest.ru.0018",
      "text": "🌳 {user} искал самый круглый жёлудь, выкопал кротовую нору и выкопал {delta} из-под коряги!"
    },
    {
      "id": "forest.ru.0019",
      "text": "🦉 {user} смотрел, как мох растёт, распугал бабочек и вытряхнул {delta} из шапки!"
    },
    {
      "id": "forest.ru.0020",
      "text": "🌿 {user} переплетал лапти у пня, вспомнил детство и стряхнул с ветки {delta} прямо на голову!"
    },
    {
      "id": "forest.ru.0021",
      "text": "🐗 {user} наблюдал за белкой на сосне, перепутал тропу и случайно зацепил {delta} лаптём!"
    },
    {
      "id": "forest.ru.0022",
      "text": "🍄 {user} переплетал лапти у пня, выкопал кротовую нору и увидел {delta} в траве и обрадовался!"
    },
    {
      "id": "forest.ru.0023",
      "text": "🌲 {user} разводил костёр в овраге, подобрал странный камень и выудил {delta} из дупла!"
    },
    {
      "id": "forest.ru.0024",
      "text": "🍂 {user} ловил эхо у скалы, выкопал кротовую нору и намерил {delta} у самого пня!"
    },
    {
      "id": "forest.ru.0025",
      "text": "🦉 {user} учился у филина мудрости, споткнулся о корни и стряхнул с ветки {delta} прямо на голову!"
    },
    {
      "id": "forest.ru.0026",
      "text": "🍄 {user} смотрел, как мох растёт, полез за грибом и намерил {delta} у самого пня!"
    },
    {
      "id": "forest.ru.0027",
      "text": "🌲 {user} рыл схрон под корягой, решил передохнуть и услышал шёпот папоротника — и стал на {delta} длиннее!"
    },
    {
      "id": "forest.ru.0028",
      "text": "🦡 {user} обходил поляну по периметру, перепутал тропу и выторговал {delta} у лесного духа!"
    },
    {
      "id": "forest.ru.0029",
      "text": "🦊 {user} слушал кукушку у ручья, вспомнил детство и выторговал {delta} у лесного духа!"
    },
    {
      "id": "forest.ru.0030",
      "text": "🍂 {user} разводил костёр в овраге, решил передохнуть и выудил {delta} из дупла!"
    },
    {
      "id": "forest.ru.0031",
      "text": "🦡 {user} выпиливал свисток из ветки, полез за грибом и выторговал {delta} у лесного духа!"
    },
    {
      "id": "forest.ru.0032",
      "text": "🍄 {user} смотрел, как мох растёт, перепутал тропу и выкопал {delta} из-под коряги!"
    },
    {
      "id": "forest.ru.0033",
      "text": "🌿 {user} смотрел, как мох растёт, распугал бабочек и случайно зацепил {delta} лаптём!"
    },
    {
      "id": "forest.ru.0034",
      "text": "🦌 {user} рыл схрон под корягой, вспомнил детство и стряхнул с ветки {delta} прямо на голову!"
    },
    {
      "id": "forest.ru.0035",
      "text": "🍂 {user} выпиливал свисток из ветки, полез за грибом и случайно зацепил {delta} лаптём!"
    },
    {
      "id": "forest.ru.0036",
      "text": "🍄 {user} плёл венок из папоротника, обнял берёзу и обнаружил {delta} прямо в мхе!"
    },
    {
      "id": "forest.ru.0037",
      "text": "🍂 {user} точил топор о валун, услышал хруст в кустах и нашёл {delta} в густой листве!"
    },
    {
      "id": "forest.ru.0038",
      "text": "🪵 {user} переплетал лапти у пня, подобрал странный камень и выкопал {delta} из-под коряги!"
    },
    {
      "id": "forest.ru.0039",
      "text": "🐺 {user} наблюдал за белкой на сосне, наткнулся на дупло и выудил {delta} из дупла!"
    },
    {
      "id": "forest.ru.0040",
      "text": "🪵 {user} выпиливал свисток из ветки, подобрал странный камень и выторговал {delta} у лесного духа!"
    },
    {
      "id": "forest.ru.0041",
      "text": "🪶 {user} рыл схрон под корягой, полез за грибом и стряхнул с ветки {delta} прямо на голову!"
    },
    {
      "id": "forest.ru.0042",
      "text": "🦡 {user} пел грустные песни ёлкам, перепутал тропу и получил {delta} в подарок от лешего!"
    },
    {
      "id": "forest.ru.0043",
      "text": "🪵 {user} рыл схрон под корягой, услышал хруст в кустах и выторговал {delta} у лесного духа!"
    },
    {
      "id": "forest.ru.0044",
      "text": "🦊 {user} искал самый круглый жёлудь, подобрал странный камень и получил {delta} в подарок от лешего!"
    },
    {
      "id": "forest.ru.0045",
      "text": "🐗 {user} переобувался на привале, перепутал тропу и увидел {delta} в траве и обрадовался!"
    },
    {
      "id": "forest.ru.0046",
      "text": "🐻 {user} переплетал лапти у пня, полез за грибом и выудил {delta} из дупла!"
    },
    {
      "id": "forest.ru.0047",
      "text": "🐗 {user} ловил эхо у скалы, повстречал ёжика и выторговал {delta} у лесного духа!"
    },
    {
      "id": "forest.ru.0048",
      "text": "🦌 {user} слушал кукушку у ручья, наткнулся на дупло и стряхнул с ветки {delta} прямо на голову!"
    },
    {
      "id": "forest.ru.0049",
      "text": "🌳 {user} учился у филина мудрости, обнял берёзу и выудил {delta} из дупла!"
    },
    {
      "id": "forest.ru.0050",
      "text": "🐗 {user} продирался сквозь чащу, вспомнил детство и намерил {delta} у самого пня!"
    },
    {
      "id": "forest.ru.0051",
      "text": "🌲 {user} слушал кукушку у ручья, поскользнулся на хвое и выторговал {delta} у лесного духа!"
    },
    {
      "id": "forest.ru.0052",
      "text": "🦊 {user} собирал грибы у старого пня, решил передохнуть и нашёл {delta} в густой листве!"
    },
    {
      "id": "forest.ru.0053",
      "text": "🐗 {user} собирал грибы у старого пня, наткнулся на дупло и выторговал {delta} у лесного духа!"
    },
    {
      "id": "forest.ru.0054",
      "text": "🦊 {user} смотрел, как мох растёт, полез за грибом и обменял свой свисток на {delta} у филина!"
    },
    {
      "id": "forest.ru.0055",
      "text": "🌳 {user} рыл схрон под корягой, распугал бабочек и обменял свой свисток на {delta} у филина!"
    },
    {
      "id": "forest.ru.0056",
      "text": "🌿 {user} наблюдал за белкой на сосне, решил передохнуть и услышал шёпот папоротника — и стал на {delta} длиннее!"
    },
    {
      "id": "forest.ru.0057",
      "text": "🦉 {user} разводил костёр в овраге, повстречал ёжика и вспомнил заветное слово — и тут же подрос на {delta}!"
    },
    {
      "id": "forest.ru.0058",
      "text": "🦉 {user} рыл схрон под корягой, поскользнулся на хвое и увидел {delta} в траве и обрадовался!"
    },
    {
      "id": "forest.ru.0059",
      "text": "🍂 {user} пел грустные песни ёлкам, наткнулся на дупло и услышал шёпот папоротника — и стал на {delta} длиннее!"
    },
    {
      "id": "forest.ru.0060",
      "text": "🦉 {user} наблюдал за белкой на сосне, обнял берёзу и нашёл {delta} в густой листве!"
    },
    {
      "id": "forest.ru.0061",
      "text": "🦊 {user} собирал грибы у старого пня, наткнулся на дупло и услышал шёпот папоротника — и стал на {delta} длиннее!"
    },
    {
      "id": "forest.ru.0062",
      "text": "🪵 {user} собирал грибы у старого пня, услышал хруст в кустах и услышал шёпот папоротника — и стал на {delta} длиннее!"
    },
    {
      "id": "forest.ru.0063",
      "text": "🐗 {user} пел грустные песни ёлкам, услышал хруст в кустах и услышал шёпот папоротника — и стал на {delta} длиннее!"
    },
    {
      "id": "forest.ru.0064",
      "text": "🪶 {user} точил палку для костра, споткнулся о корни и поднял {delta} с тропы!"
    },
    {
      "id": "forest.ru.0065",
      "text": "🦊 {user} обходил поляну по периметру, выкопал кротовую нору и обнаружил {delta} прямо в мхе!"
    },
    {
      "id": "forest.ru.0066",
      "text": "🦊 {user} смотрел, как мох растёт, посмотрел под лапник и выудил {delta} из дупла!"
    },
    {
      "id": "forest.ru.0067",
      "text": "🌳 {user} учился у филина мудрости, подобрал странный камень и вспомнил заветное слово — и тут же подрос на {delta}!"
    },
    {
      "id": "forest.ru.0068",
      "text": "🦉 {user} переплетал лапти у пня, повстречал ёжика и нашёл {delta} в густой листве!"
    },
    {
      "id": "forest.ru.0069",
      "text": "🐗 {user} продирался сквозь чащу, выкопал кротовую нору и стряхнул с ветки {delta} прямо на голову!"
    },
    {
      "id": "forest.ru.0070",
      "text": "🐗 {user} рыл схрон под корягой, споткнулся о корни и случайно зацепил {delta} лаптём!"
    },
    {
      "id": "forest.ru.0071",
      "text": "🌲 {user} точил топор о валун, решил передохнуть и выудил {delta} из дупла!"
    },
    {
      "id": "forest.ru.0072",
      "text": "🌲 {user} наблюдал за белкой на сосне, споткнулся о корни и обнаружил {delta} прямо в мхе!"
    },
    {
      "id": "forest.ru.0073",
      "text": "🦌 {user} переобувался на привале, решил передохнуть и выудил {delta} из дупла!"
    },
    {
      "id": "forest.ru.0074",
      "text": "🦡 {user} точил топор о валун, перепутал тропу и обнаружил {delta} прямо в мхе!"
    },
    {
      "id": "forest.ru.0075",
      "text": "🍂 {user} ловил эхо у скалы, поскользнулся на хвое и нашёл {delta} в густой листве!"
    },
    {
      "id": "forest.ru.0076",
      "text": "🐻 {user} разгребал муравейник палкой, споткнулся о корни и получил {delta} в подарок от лешего!"
    },
    {
      "id": "forest.ru.0077",
      "text": "🦡 {user} ловил эхо у скалы, распугал бабочек и вспомнил заветное слово — и тут же подрос на {delta}!"
    },
    {
      "id": "forest.ru.0078",
      "text": "🦌 {user} пел грустные песни ёлкам, выкопал кротовую нору и выудил {delta} из дупла!"
    },
    {
      "id": "forest.ru.0079",
      "text": "🦉 {user} точил топор о валун, поскользнулся на хвое и вытряхнул {delta} из шапки!"
    },
    {
      "id": "forest.ru.0080",
      "text": "🪵 {user} слушал кукушку у ручья, повстречал ёжика и нашёл {delta} в густой листве!"
    },
    {
      "id": "forest.ru.0081",
      "text": "🌿 {user} смотрел, как мох растёт, вспомнил детство и поднял {delta} с тропы!"
    },
    {
      "id": "forest.ru.0082",
      "text": "🦡 {user} выпиливал свисток из ветки, обнял берёзу и выудил {delta} из дупла!"
    },
    {
      "id": "forest.ru.0083",
      "text": "🍄 {user} слушал кукушку у ручья, наткнулся на дупло и выудил {delta} из дупла!"
    },
    {
      "id": "forest.ru.0084",
      "text": "🌿 {user} собирал грибы у старого пня, распугал бабочек и намерил {delta} у самого пня!"
    },
    {
      "id": "forest.ru.0085",
      "text": "🐗 {user} ловил эхо у скалы, повстречал ёжика и услышал шёпот папоротника — и стал на {delta} длиннее!"
    },
    {
      "id": "forest.ru.0086",
      "text": "🦊 {user} искал самый круглый жёлудь, решил передохнуть и увидел {delta} в траве и обрадовался!"
    },
    {
      "id": "forest.ru.0087",
      "text": "🌳 {user} переплетал лапти у пня, вспомнил детство и нашёл {delta} в густой листве!"
    },
    {
      "id": "forest.ru.0088",
      "text": "🦡 {user} плёл венок из папоротника, поскользнулся на хвое и стряхнул с ветки {delta} прямо на голову!"
    },
    {
      "id": "forest.ru.0089",
      "text": "🦊 {user} пел грустные песни ёлкам, споткнулся о корни и выудил {delta} из дупла!"
    },
    {
      "id": "forest.ru.0090",
      "text": "🪵 {user} переплетал лапти у пня, посмотрел под лапник и намерил {delta} у самого пня!"
    },
    {
      "id": "forest.ru.0091",
      "text": "🐻 {user} учился у филина мудрости, подобрал странный камень и случайно зацепил {delta} лаптём!"
    },
    {
      "id": "forest.ru.0092",
      "text": "🦊 {user} собирал грибы у старого пня, повстречал ёжика и вытряхнул {delta} из шапки!"
    },
    {
      "id": "forest.ru.0093",
      "text": "🦌 {user} продирался сквозь чащу, перепутал тропу и выкопал {delta} из-под коряги!"
    },
    {
      "id": "forest.ru.0094",
      "text": "🐿️ {user} ловил эхо у скалы, обнял берёзу и поднял {delta} с тропы!"
    },
    {
      "id": "forest.ru.0095",
      "text": "🍄 {user} учился у филина мудрости, подобрал странный камень и нашёл {delta} в густой листве!"
    },
    {
      "id": "forest.ru.0096",
      "text": "🐺 {user} обходил поляну по периметру, подобрал странный камень и вытряхнул {delta} из шапки!"
    },
    {
      "id": "forest.ru.0097",
      "text": "🍄 {user} разгребал муравейник палкой, поскользнулся на хвое и стряхнул с ветки {delta} прямо на голову!"
    },
    {
      "id": "forest.ru.0098",
      "text": "🍂 {user} пел грустные песни ёлкам, наткнулся на дупло и обменял свой свисток на {delta} у филина!"
    },
    {
      "id": "forest.ru.0099",
      "text": "🦌 {user} пугал лису свистом, выкопал кротовую нору и услышал шёпот папоротника — и стал на {delta} длиннее!"
    },
    {
      "id": "forest.ru.0100",
      "text": "🪶 {user} разводил костёр в овраге, наткнулся на дупло и вытряхнул {delta} из шапки!"
    },
    {
      "id": "forest.ru.0101",
      "text": "🐻 {user} разводил костёр в овраге, обнял берёзу и получил {delta} в подарок от лешего!"
    },
    {
      "id": "forest.ru.0102",
      "text": "🪵 {user} искал самый круглый жёлудь, поскользнулся на хвое и стряхнул с ветки {delta} прямо на голову!"
    },
    {
      "id": "forest.ru.0103",
      "text": "🐻 {user} точил топор о валун, наткнулся на дупло и случайно зацепил {delta} лаптём!"
    },
    {
      "id": "forest.ru.0104",
      "text": "🦡 {user} переплетал лапти у пня, решил передохнуть и выкопал {delta} из-под коряги!"
    },
    {
      "id": "forest.ru.0105",
      "text": "🐻 {user} пел грустные песни ёлкам, подобрал странный камень и намерил {delta} у самого пня!"
    },
    {
      "id": "forest.ru.0106",
      "text": "🍄 {user} разгребал муравейник палкой, выкопал кротовую нору и выудил {delta} из дупла!"
    },
    {
      "id": "forest.ru.0107",
      "text": "🦡 {user} выпиливал свисток из ветки, повстречал ёжика и нашёл {delta} в густой листве!"
    },
    {
      "id": "forest.ru.0108",
      "text": "🦡 {user} точил палку для костра, решил передохнуть и выторговал {delta} у лесного духа!"
    },
    {
      "id": "forest.ru.0109",
      "text": "🦉 {user} переобувался на привале, споткнулся о корни и вспомнил заветное слово — и тут же подрос на {delta}!"
    },
    {
      "id": "forest.ru.0110",
      "text": "🌳 {user} смотрел, как мох растёт, перепутал тропу и услышал шёпот папоротника — и стал на {delta} длиннее!"
    },
    {
      "id": "forest.ru.0111",
      "text": "🪶 {user} точил топор о валун, подобрал странный камень и вспомнил заветное слово — и тут же подрос на {delta}!"
    },
    {
      "id": "forest.ru.0112",
      "text": "🍂 {user} точил палку для костра, решил передохнуть и нашёл {delta} в густой листве!"
    },
    {
      "id": "forest.ru.0113",
      "text": "🦉 {user} плёл венок из папоротника, выкопал кротовую нору и получил {delta} в подарок от лешего!"
    },
    {
      "id": "forest.ru.0114",
      "text": "🍂 {user} слушал кукушку у ручья, полез за грибом и поднял {delta} с тропы!"
    },
    {
      "id": "forest.ru.0115",
      "text": "🪵 {user} переобувался на привале, поскользнулся на хвое и вытряхнул {delta} из шапки!"
    },
    {
      "id": "forest.ru.0116",
      "text": "🦊 {user} переплетал лапти у пня, распугал бабочек и стряхнул с ветки {delta} прямо на голову!"
    },
    {
      "id": "forest.ru.0117",
      "text": "🐻 {user} разводил костёр в овраге, выкопал кротовую нору и вытряхнул {delta} из шапки!"
    },
    {
      "id": "forest.ru.0118",
      "text": "🦉 {user} пел грустные песни ёлкам, полез за грибом и получил {delta} в подарок от лешего!"
    },
    {
      "id": "forest.ru.0119",
      "text": "🐗 {user} слушал кукушку у ручья, перепутал тропу и выкопал {delta} из-под коряги!"
    },
    {
      "id": "forest.ru.0120",
      "text": "🌿 {user} разгребал муравейник палкой, повстречал ёжика и намерил {delta} у самого пня!"
    },
    {
      "id": "forest.ru.0121",
      "text": "🐗 {user} учился у филина мудрости, подобрал странный камень и обменял свой свисток на {delta} у филина!"
    },
    {
      "id": "forest.ru.0122",
      "text": "🐺 {user} точил топор о валун, решил передохнуть и намерил {delta} у самого пня!"
    },
    {
      "id": "forest.ru.0123",
      "text": "🍂 {user} плёл венок из папоротника, услышал хруст в кустах и выторговал {delta} у лесного духа!"
    },
    {
      "id": "forest.ru.0124",
      "text": "🌳 {user} наблюдал за белкой на сосне, полез за грибом и увидел {delta} в траве и обрадовался!"
    },
    {
      "id": "forest.ru.0125",
      "text": "🌿 {user} плёл венок из папоротника, повстречал ёжика и нашёл {delta} в густой листве!"
    },
    {
      "id": "forest.ru.0126",
      "text": "🌳 {user} точил топор о валун, подобрал странный камень и выкопал {delta} из-под коряги!"
    },
    {
      "id": "forest.ru.0127",
      "text": "🍂 {user} пугал лису свистом, споткнулся о корни и вспомнил заветное слово — и тут же подрос на {delta}!"
    },
    {
      "id": "forest.ru.0128",
      "text": "🐺 {user} переплетал лапти у пня, полез за грибом и получил {delta} в подарок от лешего!"
    },
    {
      "id": "forest.ru.0129",
      "text": "🌿 {user} собирал грибы у старого пня, споткнулся о корни и вспомнил заветное слово — и тут же подрос на {delta}!"
    },
    {
      "id": "forest.ru.0130",
      "text": "🐺 {user} переплетал лапти у пня, споткнулся о корни и выудил {delta} из дупла!"
    },
    {
      "id": "forest.ru.0131",
      "text": "🍄 {user} учился у филина мудрости, полез за грибом и выторговал {delta} у лесного духа!"
    },
    {
      "id": "forest.ru.0132",
      "text": "🐿️ {user} учился у филина мудрости, решил передохнуть и намерил {delta} у самого пня!"
    },
    {
      "id": "forest.ru.0133",
      "text": "🐗 {user} переплетал лапти у пня, полез за грибом и увидел {delta} в траве и обрадовался!"
    },
    {
      "id": "forest.ru.0134",
      "text": "🐿️ {user} плёл венок из папоротника, выкопал кротовую нору и вспомнил заветное слово — и тут же подрос на {delta}!"
    },
    {
      "id": "forest.ru.0135",
      "text": "🪵 {user} выпиливал свисток из ветки, споткнулся о корни и услышал шёпот папоротника — и стал на {delta} длиннее!"
    },
    {
      "id": "forest.ru.0136",
      "text": "🐿️ {user} разводил костёр в овраге, обнял берёзу и нашёл {delta} в густой листве!"
    },
    {
      "id": "forest.ru.0137",
      "text": "🌳 {user} обходил поляну по периметру, распугал бабочек и получил {delta} в подарок от лешего!"
    },
    {
      "id": "forest.ru.0138",
      "text": "🌲 {user} разводил костёр в овраге, посмотрел под лапник и выудил {delta} из дупла!"
    },
    {
      "id": "forest.ru.0139",
      "text": "🐿️ {user} обходил поляну по периметру, обнял берёзу и обнаружил {delta} прямо в мхе!"
    },
    {
      "id": "forest.ru.0140",
      "text": "🐗 {user} точил палку для костра, перепутал тропу и выудил {delta} из дупла!"
    },
    {
      "id": "forest.ru.0141",
      "text": "🌿 {user} точил топор о валун, подобрал странный камень и намерил {delta} у самого пня!"
    },
    {
      "id": "forest.ru.0142",
      "text": "🍂 {user} выпиливал свисток из ветки, повстречал ёжика и увидел {delta} в траве и обрадовался!"
    },
    {
      "id": "forest.ru.0143",
      "text": "🍄 {user} пел грустные песни ёлкам, услышал хруст в кустах и намерил {delta} у самого пня!"
    },
    {
      "id": "forest.ru.0144",
      "text": "🍄 {user} разгребал муравейник палкой, споткнулся о корни и выторговал {delta} у лесного духа!"
    },
    {
      "id": "forest.ru.0145",
      "text": "🐺 {user} плёл венок из папоротника, вспомнил детство и поднял {delta} с тропы!"
    },
    {
      "id": "forest.ru.0146",
      "text": "🦊 {user} обходил поляну по периметру, распугал бабочек и стряхнул с ветки {delta} прямо на голову!"
    },
    {
      "id": "forest.ru.0147",
      "text": "🪶 {user} точил палку для костра, перепутал тропу и случайно зацепил {delta} лаптём!"
    },
    {
      "id": "forest.ru.0148",
      "text": "🌲 {user} слушал кукушку у ручья, посмотрел под лапник и обменял свой свисток на {delta} у филина!"
    },
    {
      "id": "forest.ru.0149",
      "text": "🦉 {user} разгребал муравейник палкой, услышал хруст в кустах и выудил {delta} из дупла!"
    },
    {
      "id": "forest.ru.0150",
      "text": "🐻 {user} смотрел, как мох растёт, споткнулся о корни и намерил {delta} у самого пня!"
    },
    {
      "id": "forest.ru.0151",
      "text": "🌿 {user} выпиливал свисток из ветки, подобрал странный камень и обнаружил {delta} прямо в мхе!"
    },
    {
      "id": "forest.ru.0152",
      "text": "🦡 {user} продирался сквозь чащу, услышал хруст в кустах и нашёл {delta} в густой листве!"
    },
    {
      "id": "forest.ru.0153",
      "text": "🦡 {user} учился у филина мудрости, повстречал ёжика и случайно зацепил {delta} лаптём!"
    },
    {
      "id": "forest.ru.0154",
      "text": "🍄 {user} переобувался на привале, посмотрел под лапник и стряхнул с ветки {delta} прямо на голову!"
    },
    {
      "id": "forest.ru.0155",
      "text": "🦡 {user} учился у филина мудрости, поскользнулся на хвое и выкопал {delta} из-под коряги!"
    },
    {
      "id": "forest.ru.0156",
      "text": "🍂 {user} переобувался на привале, решил передохнуть и обнаружил {delta} прямо в мхе!"
    },
    {
      "id": "forest.ru.0157",
      "text": "🐿️ {user} плёл венок из папоротника, повстречал ёжика и увидел {delta} в траве и обрадовался!"
    },
    {
      "id": "forest.ru.0158",
      "text": "🐺 {user} переплетал лапти у пня, услышал хруст в кустах и услышал шёпот папоротника — и стал на {delta} длиннее!"
    },
    {
      "id": "forest.ru.0159",
      "text": "🐗 {user} продирался сквозь чащу, выкопал кротовую нору и получил {delta} в подарок от лешего!"
    },
    {
      "id": "forest.ru.0160",
      "text": "🐻 {user} переобувался на привале, подобрал странный камень и обменял свой свисток на {delta} у филина!"
    },
    {
      "id": "forest.ru.0161",
      "text": "🐻 {user} искал самый круглый жёлудь, вспомнил детство и стряхнул с ветки {delta} прямо на голову!"
    },
    {
      "id": "forest.ru.0162",
      "text": "🐺 {user} плёл венок из папоротника, решил передохнуть и услышал шёпот папоротника — и стал на {delta} длиннее!"
    },
    {
      "id": "forest.ru.0163",
      "text": "🦉 {user} обходил поляну по периметру, повстречал ёжика и нашёл {delta} в густой листве!"
    },
    {
      "id": "forest.ru.0164",
      "text": "🐻 {user} разгребал муравейник палкой, наткнулся на дупло и увидел {delta} в траве и обрадовался!"
    },
    {
      "id": "forest.ru.0165",
      "text": "🦌 {user} обходил поляну по периметру, вспомнил детство и услышал шёпот папоротника — и стал на {delta} длиннее!"
    },
    {
      "id": "forest.ru.0166",
      "text": "🪵 {user} искал самый круглый жёлудь, выкопал кротовую нору и нашёл {delta} в густой листве!"
    },
    {
      "id": "forest.ru.0167",
      "text": "🦌 {user} выпиливал свисток из ветки, полез за грибом и вытряхнул {delta} из шапки!"
    },
    {
      "id": "forest.ru.0168",
      "text": "🦊 {user} переплетал лапти у пня, обнял берёзу и обменял свой свисток на {delta} у филина!"
    },
    {
      "id": "forest.ru.0169",
      "text": "🐗 {user} переобувался на привале, распугал бабочек и получил {delta} в подарок от лешего!"
    },
    {
      "id": "forest.ru.0170",
      "text": "🦊 {user} пел грустные песни ёлкам, выкопал кротовую нору и обнаружил {delta} прямо в мхе!"
    },
    {
      "id": "forest.ru.0171",
      "text": "🌲 {user} пугал лису свистом, решил передохнуть и получил {delta} в подарок от лешего!"
    },
    {
      "id": "forest.ru.0172",
      "text": "🐻 {user} искал самый круглый жёлудь, поскользнулся на хвое и увидел {delta} в траве и обрадовался!"
    },
    {
      "id": "forest.ru.0173",
      "text": "🦡 {user} переплетал лапти у пня, полез за грибом и выкопал {delta} из-под коряги!"
    },
    {
      "id": "forest.ru.0174",
      "text": "🪶 {user} разгребал муравейник палкой, вспомнил детство и обменял свой свисток на {delta} у филина!"
    },
    {
      "id": "forest.ru.0175",
      "text": "🦊 {user} наблюдал за белкой на сосне, выкопал кротовую нору и услышал шёпот папоротника — и стал на {delta} длиннее!"
    },
    {
      "id": "forest.ru.0176",
      "text": "🐿️ {user} разгребал муравейник палкой, перепутал тропу и случайно зацепил {delta} лаптём!"
    },
    {
      "id": "forest.ru.0177",
      "text": "🍄 {user} плёл венок из папоротника, повстречал ёжика и нашёл {delta} в густой листве!"
    },
    {
      "id": "forest.ru.0178",
      "text": "🍂 {user} точил палку для костра, полез за грибом и нашёл {delta} в густой листве!"
    },
    {
      "id": "forest.ru.0179",
      "text": "🍂 {user} плёл венок из папоротника, вспомнил детство и увидел {delta} в траве и обрадовался!"
    },
    {
      "id": "forest.ru.0180",
      "text": "🪶 {user} рыл схрон под корягой, решил передохнуть и услышал шёпот папоротника — и стал на {delta} длиннее!"
    },
    {
      "id": "forest.ru.0181",
      "text": "🌳 {user} обходил поляну по периметру, обнял берёзу и выкопал {delta} из-под коряги!"
    },
    {
      "id": "forest.ru.0182",
      "text": "🐻 {user} пугал лису свистом, поскользнулся на хвое и случайно зацепил {delta} лаптём!"
    },
    {
      "id": "forest.ru.0183",
      "text": "🐿️ {user} разводил костёр в овраге, обнял берёзу и стряхнул с ветки {delta} прямо на голову!"
    },
    {
      "id": "forest.ru.0184",
      "text": "🐺 {user} точил палку для костра, повстречал ёжика и нашёл {delta} в густой листве!"
    },
    {
      "id": "forest.ru.0185",
      "text": "🐺 {user} ловил эхо у скалы, распугал бабочек и обнаружил {delta} прямо в мхе!"
    },
    {
      "id": "forest.ru.0186",
      "text": "🌲 {user} пел грустные песни ёлкам, споткнулся о корни и стряхнул с ветки {delta} прямо на голову!"
    },
    {
      "id": "forest.ru.0187",
      "text": "🐗 {user} плёл венок из папоротника, вспомнил детство и выкопал {delta} из-под коряги!"
    },
    {
      "id": "forest.ru.0188",
      "text": "🦡 {user} продирался сквозь чащу, обнял берёзу и выторговал {delta} у лесного духа!"
    },
    {
      "id": "forest.ru.0189",
      "text": "🌲 {user} переобувался на привале, услышал хруст в кустах и нашёл {delta} в густой листве!"
    },
    {
      "id": "forest.ru.0190",
      "text": "🦡 {user} точил топор о валун, подобрал странный камень и выторговал {delta} у лесного духа!"
    },
    {
      "id": "forest.ru.0191",
      "text": "🦊 {user} пугал лису свистом, решил передохнуть и поднял {delta} с тропы!"
    },
    {
      "id": "forest.ru.0192",
      "text": "🦊 {user} смотрел, как мох растёт, решил передохнуть и выторговал {delta} у лесного духа!"
    },
    {
      "id": "forest.ru.0193",
      "text": "🐻 {user} пугал лису свистом, наткнулся на дупло и выторговал {delta} у лесного духа!"
    },
    {
      "id": "forest.ru.0194",
      "text": "🦉 {user} точил палку для костра, распугал бабочек и намерил {delta} у самого пня!"
    },
    {
      "id": "forest.ru.0195",
      "text": "🍂 {user} ловил эхо у скалы, повстречал ёжика и случайно зацепил {delta} лаптём!"
    },
    {
      "id": "forest.ru.0196",
      "text": "🍂 {user} пугал лису свистом, обнял берёзу и выторговал {delta} у лесного духа!"
    },
    {
      "id": "forest.ru.0197",
      "text": "🌳 {user} пугал лису свистом, распугал бабочек и намерил {delta} у самого пня!"
    },
    {
      "id": "forest.ru.0198",
      "text": "🐺 {user} наблюдал за белкой на сосне, распугал бабочек и выудил {delta} из дупла!"
    },
    {
      "id": "forest.ru.0199",
      "text": "🌲 {user} точил палку для костра, споткнулся о корни и вытряхнул {delta} из шапки!"
    },
    {
      "id": "forest.ru.0200",
      "text": "🪵 {user} точил топор о валун, споткнулся о корни и обменял свой свисток на {delta} у филина!"
    },
    {
      "id": "forest.ru.0201",
      "text": "🪶 {user} наблюдал за белкой на сосне, повстречал ёжика и выкопал {delta} из-под коряги!"
    },
    {
      "id": "forest.ru.0202",
      "text": "🍄 {user} ловил эхо у скалы, повстречал ёжика и увидел {delta} в траве и обрадовался!"
    },
    {
      "id": "forest.ru.0203",
      "text": "🍂 {user} учился у филина мудрости, поскользнулся на хвое и выторговал {delta} у лесного духа!"
    },
    {
      "id": "forest.ru.0204",
      "text": "🍂 {user} рыл схрон под корягой, услышал хруст в кустах и вытряхнул {delta} из шапки!"
    },
    {
      "id": "forest.ru.0205",
      "text": "🍄 {user} выпиливал свисток из ветки, решил передохнуть и намерил {delta} у самого пня!"
    },
    {
      "id": "forest.ru.0206",
      "text": "🦉 {user} учился у филина мудрости, наткнулся на дупло и намерил {delta} у самого пня!"
    },
    {
      "id": "forest.ru.0207",
      "text": "🌿 {user} пел грустные песни ёлкам, полез за грибом и выторговал {delta} у лесного духа!"
    },
    {
      "id": "forest.ru.0208",
      "text": "🦌 {user} точил палку для костра, выкопал кротовую нору и выторговал {delta} у лесного духа!"
    },
    {
      "id": "forest.ru.0209",
      "text": "🪶 {user} наблюдал за белкой на сосне, услышал хруст в кустах и увидел {delta} в траве и обрадовался!"
    },
    {
      "id": "forest.ru.0210",
      "text": "🌳 {user} учился у филина мудрости, наткнулся на дупло и поднял {delta} с тропы!"
    },
    {
      "id": "forest.ru.0211",
      "text": "🪵 {user} обходил поляну по периметру, выкопал кротовую нору и намерил {delta} у самого пня!"
    },
    {
      "id": "forest.ru.0212",
      "text": "🪶 {user} выпиливал свисток из ветки, поскользнулся на хвое и случайно зацепил {delta} лаптём!"
    },
    {
      "id": "forest.ru.0213",
      "text": "🐻 {user} плёл венок из папоротника, повстречал ёжика и выторговал {delta} у лесного духа!"
    },
    {
      "id": "forest.ru.0214",
      "text": "🌳 {user} пел грустные песни ёлкам, распугал бабочек и стряхнул с ветки {delta} прямо на голову!"
    },
    {
      "id": "forest.ru.0215",
      "text": "🐿️ {user} пел грустные песни ёлкам, поскользнулся на хвое и услышал шёпот папоротника — и стал на {delta} длиннее!"
    },
    {
      "id": "forest.ru.0216",
      "text": "🐻 {user} искал самый круглый жёлудь, обнял берёзу и намерил {delta} у самого пня!"
    },
    {
      "id": "forest.ru.0217",
      "text": "🍂 {user} искал самый круглый жёлудь, вспомнил детство и нашёл {delta} в густой листве!"
    },
    {
      "id": "forest.ru.0218",
      "text": "🪵 {user} обходил поляну по периметру, подобрал странный камень и намерил {delta} у самого пня!"
    },
    {
      "id": "forest.ru.0219",
      "text": "🐿️ {user} точил топор о валун, повстречал ёжика и намерил {delta} у самого пня!"
    },
    {
      "id": "forest.ru.0220",
      "text": "🐻 {user} точил палку для костра, наткнулся на дупло и случайно зацепил {delta} лаптём!"
    },
    {
      "id": "forest.ru.0221",
      "text": "🐻 {user} точил топор о валун, перепутал тропу и намерил {delta} у самого пня!"
    },
    {
      "id": "forest.ru.0222",
      "text": "🌳 {user} искал самый круглый жёлудь, повстречал ёжика и нашёл {delta} в густой листве!"
    },
    {
      "id": "forest.ru.0223",
      "text": "🦊 {user} переплетал лапти у пня, повстречал ёжика и вспомнил заветное слово — и тут же подрос на {delta}!"
    },
    {
      "id": "forest.ru.0224",
      "text": "🌿 {user} смотрел, как мох растёт, подобрал странный камень и случайно зацепил {delta} лаптём!"
    },
    {
      "id": "forest.ru.0225",
      "text": "🪵 {user} разводил костёр в овраге, повстречал ёжика и услышал шёпот папоротника — и стал на {delta} длиннее!"
    },
    {
      "id": "forest.ru.0226",
      "text": "🐗 {user} переплетал лапти у пня, посмотрел под лапник и выкопал {delta} из-под коряги!"
    },
    {
      "id": "forest.ru.0227",
      "text": "🪶 {user} пел грустные песни ёлкам, посмотрел под лапник и обнаружил {delta} прямо в мхе!"
    },
    {
      "id": "forest.ru.0228",
      "text": "🌳 {user} выпиливал свисток из ветки, повстречал ёжика и обменял свой свисток на {delta} у филина!"
    },
    {
      "id": "forest.ru.0229",
      "text": "🌳 {user} собирал грибы у старого пня, услышал хруст в кустах и получил {delta} в подарок от лешего!"
    },
    {
      "id": "forest.ru.0230",
      "text": "🍂 {user} рыл схрон под корягой, выкопал кротовую нору и увидел {delta} в траве и обрадовался!"
    },
    {
      "id": "forest.ru.0231",
      "text": "🦡 {user} точил палку для костра, выкопал кротовую нору и выудил {delta} из дупла!"
    },
    {
      "id": "forest.ru.0232",
      "text": "🐻 {user} переплетал лапти у пня, полез за грибом и увидел {delta} в траве и обрадовался!"
    },
    {
      "id": "forest.ru.0233",
      "text": "🪶 {user} продирался сквозь чащу, распугал бабочек и случайно зацепил {delta} лаптём!"
    },
    {
      "id": "forest.ru.0234",
      "text": "🍂 {user} наблюдал за белкой на сосне, услышал хруст в кустах и намерил {delta} у самого пня!"
    },
    {
      "id": "forest.ru.0235",
      "text": "🌿 {user} собирал грибы у старого пня, посмотрел под лапник и намерил {delta} у самого пня!"
    },
    {
      "id": "forest.ru.0236",
      "text": "🌿 {user} наблюдал за белкой на сосне, вспомнил детство и получил {delta} в подарок от лешего!"
    },
    {
      "id": "forest.ru.0237",
      "text": "🌿 {user} собирал грибы у старого пня, повстречал ёжика и случайно зацепил {delta} лаптём!"
    },
    {
      "id": "forest.ru.0238",
      "text": "🦊 {user} пел грустные песни ёлкам, выкопал кротовую нору и получил {delta} в подарок от лешего!"
    },
    {
      "id": "forest.ru.0239",
      "text": "🌳 {user} ловил эхо у скалы, решил передохнуть и нашёл {delta} в густой листве!"
    },
    {
      "id": "forest.ru.0240",
      "text": "🦌 {user} точил топор о валун, выкопал кротовую нору и намерил {delta} у самого пня!"
    },
    {
      "id": "forest.ru.0241",
      "text": "🐺 {user} разгребал муравейник палкой, вспомнил детство и услышал шёпот папоротника — и стал на {delta} длиннее!"
    },
    {
      "id": "forest.ru.0242",
      "text": "🦌 {user} плёл венок из папоротника, подобрал странный камень и случайно зацепил {delta} лаптём!"
    },
    {
      "id": "forest.ru.0243",
      "text": "🐿️ {user} искал самый круглый жёлудь, обнял берёзу и нашёл {delta} в густой листве!"
    },
    {
      "id": "forest.ru.0244",
      "text": "🪵 {user} обходил поляну по периметру, обнял берёзу и обменял свой свисток на {delta} у филина!"
    },
    {
      "id": "forest.ru.0245",
      "text": "🪵 {user} точил топор о валун, подобрал странный камень и увидел {delta} в траве и обрадовался!"
    },
    {
      "id": "forest.ru.0246",
      "text": "🍄 {user} плёл венок из папоротника, вспомнил детство и выторговал {delta} у лесного духа!"
    },
    {
      "id": "forest.ru.0247",
      "text": "🪵 {user} обходил поляну по периметру, решил передохнуть и стряхнул с ветки {delta} прямо на голову!"
    },
    {
      "id": "forest.ru.0248",
      "text": "🐿️ {user} пел грустные песни ёлкам, выкопал кротовую нору и нашёл {delta} в густой листве!"
    },
    {
      "id": "forest.ru.0249",
      "text": "🌲 {user} разгребал муравейник палкой, наткнулся на дупло и услышал шёпот папоротника — и стал на {delta} длиннее!"
    },
    {
      "id": "forest.ru.0250",
      "text": "🦌 {user} переобувался на привале, подобрал странный камень и обнаружил {delta} прямо в мхе!"
    },
    {
      "id": "forest.ru.0251",
      "text": "🐻 {user} переплетал лапти у пня, споткнулся о корни и случайно зацепил {delta} лаптём!"
    },
    {
      "id": "forest.ru.0252",
      "text": "🐺 {user} продирался сквозь чащу, поскользнулся на хвое и вспомнил заветное слово — и тут же подрос на {delta}!"
    },
    {
      "id": "forest.ru.0253",
      "text": "🐺 {user} наблюдал за белкой на сосне, подобрал странный камень и увидел {delta} в траве и обрадовался!"
    },
    {
      "id": "forest.ru.0254",
      "text": "🌿 {user} ловил эхо у скалы, распугал бабочек и выкопал {delta} из-под коряги!"
    },
    {
      "id": "forest.ru.0255",
      "text": "🦉 {user} искал самый круглый жёлудь, услышал хруст в кустах и намерил {delta} у самого пня!"
    },
    {
      "id": "forest.ru.0256",
      "text": "🪵 {user} смотрел, как мох растёт, обнял берёзу и случайно зацепил {delta} лаптём!"
    },
    {
      "id": "forest.ru.0257",
      "text": "🐗 {user} пугал лису свистом, наткнулся на дупло и стряхнул с ветки {delta} прямо на голову!"
    },
    {
      "id": "forest.ru.0258",
      "text": "🌿 {user} выпиливал свисток из ветки, решил передохнуть и вытряхнул {delta} из шапки!"
    },
    {
      "id": "forest.ru.0259",
      "text": "🍄 {user} точил топор о валун, вспомнил детство и обнаружил {delta} прямо в мхе!"
    },
    {
      "id": "forest.ru.0260",
      "text": "🌲 {user} смотрел, как мох растёт, услышал хруст в кустах и выудил {delta} из дупла!"
    },
    {
      "id": "forest.ru.0261",
      "text": "🦉 {user} переплетал лапти у пня, распугал бабочек и выторговал {delta} у лесного духа!"
    },
    {
      "id": "forest.ru.0262",
      "text": "🦉 {user} разводил костёр в овраге, услышал хруст в кустах и случайно зацепил {delta} лаптём!"
    },
    {
      "id": "forest.ru.0263",
      "text": "🦌 {user} переобувался на привале, распугал бабочек и вспомнил заветное слово — и тут же подрос на {delta}!"
    },
    {
      "id": "forest.ru.0264",
      "text": "🌿 {user} разгребал муравейник палкой, поскользнулся на хвое и выкопал {delta} из-под коряги!"
    },
    {
      "id": "forest.ru.0265",
      "text": "🪶 {user} переобувался на привале, подобрал странный камень и случайно зацепил {delta} лаптём!"
    },
    {
      "id": "forest.ru.0266",
      "text": "🍄 {user} разводил костёр в овраге, услышал хруст в кустах и нашёл {delta} в густой листве!"
    },
    {
      "id": "forest.ru.0267",
      "text": "🍄 {user} разводил костёр в овраге, подобрал странный камень и выкопал {delta} из-под коряги!"
    },
    {
      "id": "forest.ru.0268",
      "text": "🐗 {user} пел грустные песни ёлкам, решил передохнуть и услышал шёпот папоротника — и стал на {delta} длиннее!"
    },
    {
      "id": "forest.ru.0269",
      "text": "🦊 {user} собирал грибы у старого пня, посмотрел под лапник и обнаружил {delta} прямо в мхе!"
    },
    {
      "id": "forest.ru.0270",
      "text": "🌳 {user} разводил костёр в овраге, решил передохнуть и вспомнил заветное слово — и тут же подрос на {delta}!"
    },
    {
      "id": "forest.ru.0271",
      "text": "🪵 {user} собирал грибы у старого пня, полез за грибом и нашёл {delta} в густой листве!"
    },
    {
      "id": "forest.ru.0272",
      "text": "🐻 {user} собирал грибы у старого пня, поскользнулся на хвое и обнаружил {delta} прямо в мхе!"
    },
    {
      "id": "forest.ru.0273",
      "text": "🦡 {user} ловил эхо у скалы, подобрал странный камень и случайно зацепил {delta} лаптём!"
    },
    {
      "id": "forest.ru.0274",
      "text": "🦌 {user} точил топор о валун, подобрал странный камень и намерил {delta} у самого пня!"
    },
    {
      "id": "forest.ru.0275",
      "text": "🌲 {user} переплетал лапти у пня, споткнулся о корни и намерил {delta} у самого пня!"
    },
    {
      "id": "forest.ru.0276",
      "text": "🦉 {user} продирался сквозь чащу, услышал хруст в кустах и получил {delta} в подарок от лешего!"
    },
    {
      "id": "forest.ru.0277",
      "text": "🦌 {user} пел грустные песни ёлкам, наткнулся на дупло и нашёл {delta} в густой листве!"
    },
    {
      "id": "forest.ru.0278",
      "text": "🦌 {user} пугал лису свистом, перепутал тропу и увидел {delta} в траве и обрадовался!"
    },
    {
      "id": "forest.ru.0279",
      "text": "🪶 {user} продирался сквозь чащу, споткнулся о корни и увидел {delta} в траве и обрадовался!"
    },
    {
      "id": "forest.ru.0280",
      "text": "🍄 {user} смотрел, как мох растёт, споткнулся о корни и выторговал {delta} у лесного духа!"
    },
    {
      "id": "forest.ru.0281",
      "text": "🐗 {user} смотрел, как мох растёт, выкопал кротовую нору и обменял свой свисток на {delta} у филина!"
    },
    {
      "id": "forest.ru.0282",
      "text": "🦊 {user} слушал кукушку у ручья, полез за грибом и нашёл {delta} в густой листве!"
    },
    {
      "id": "forest.ru.0283",
      "text": "🐺 {user} выпиливал свисток из ветки, полез за грибом и намерил {delta} у самого пня!"
    },
    {
      "id": "forest.ru.0284",
      "text": "🦊 {user} выпиливал свисток из ветки, распугал бабочек и обнаружил {delta} прямо в мхе!"
    },
    {
      "id": "forest.ru.0285",
      "text": "🐗 {user} наблюдал за белкой на сосне, наткнулся на дупло и стряхнул с ветки {delta} прямо на голову!"
    },
    {
      "id": "forest.ru.0286",
      "text": "🐻 {user} учился у филина мудрости, полез за грибом и выторговал {delta} у лесного духа!"
    },
    {
      "id": "forest.ru.0287",
      "text": "🐗 {user} переплетал лапти у пня, поскользнулся на хвое и поднял {delta} с тропы!"
    },
    {
      "id": "forest.ru.0288",
      "text": "🦌 {user} разводил костёр в овраге, повстречал ёжика и намерил {delta} у самого пня!"
    },
    {
      "id": "forest.ru.0289",
      "text": "🍂 {user} разводил костёр в овраге, наткнулся на дупло и услышал шёпот папоротника — и стал на {delta} длиннее!"
    },
    {
      "id": "forest.ru.0290",
      "text": "🍂 {user} точил палку для костра, услышал хруст в кустах и случайно зацепил {delta} лаптём!"
    },
    {
      "id": "forest.ru.0291",
      "text": "🐗 {user} учился у филина мудрости, повстречал ёжика и выторговал {delta} у лесного духа!"
    },
    {
      "id": "forest.ru.0292",
      "text": "🌿 {user} учился у филина мудрости, споткнулся о корни и получил {delta} в подарок от лешего!"
    },
    {
      "id": "forest.ru.0293",
      "text": "🐻 {user} пел грустные песни ёлкам, перепутал тропу и выудил {delta} из дупла!"
    },
    {
      "id": "forest.ru.0294",
      "text": "🌲 {user} пел грустные песни ёлкам, споткнулся о корни и случайно зацепил {delta} лаптём!"
    },
    {
      "id": "forest.ru.0295",
      "text": "🦌 {user} пугал лису свистом, обнял берёзу и вытряхнул {delta} из шапки!"
    },
    {
      "id": "forest.ru.0296",
      "text": "🌳 {user} плёл венок из папоротника, перепутал тропу и вспомнил заветное слово — и тут же подрос на {delta}!"
    },
    {
      "id": "forest.ru.0297",
      "text": "🐻 {user} разгребал муравейник палкой, решил передохнуть и поднял {delta} с тропы!"
    },
    {
      "id": "forest.ru.0298",
      "text": "🌲 {user} точил палку для костра, споткнулся о корни и выторговал {delta} у лесного духа!"
    },
    {
      "id": "forest.ru.0299",
      "text": "🌲 {user} пел грустные песни ёлкам, подобрал странный камень и стряхнул с ветки {delta} прямо на голову!"
    },
    {
      "id": "forest.ru.0300",
      "text": "🐗 {user} смотрел, как мох растёт, вспомнил детство и услышал шёпот папоротника — и стал на {delta} длиннее!"
    },
    {
      "id": "forest.ru.0301",
      "text": "🌳 {user} точил палку для костра, услышал хруст в кустах и увидел {delta} в траве и обрадовался!"
    },
    {
      "id": "forest.ru.0302",
      "text": "🪵 {user} смотрел, как мох растёт, решил передохнуть и поднял {delta} с тропы!"
    },
    {
      "id": "forest.ru.0303",
      "text": "🐻 {user} учился у филина мудрости, услышал хруст в кустах и получил {delta} в подарок от лешего!"
    },
    {
      "id": "forest.ru.0304",
      "text": "🪵 {user} плёл венок из папоротника, посмотрел под лапник и намерил {delta} у самого пня!"
    },
    {
      "id": "forest.ru.0305",
      "text": "🦌 {user} переобувался на привале, решил передохнуть и нашёл {delta} в густой листве!"
    },
    {
      "id": "forest.ru.0306",
      "text": "🌿 {user} пел грустные песни ёлкам, распугал бабочек и выудил {delta} из дупла!"
    },
    {
      "id": "forest.ru.0307",
      "text": "🪶 {user} точил палку для костра, выкопал кротовую нору и услышал шёпот папоротника — и стал на {delta} длиннее!"
    },
    {
      "id": "forest.ru.0308",
      "text": "🌲 {user} искал самый круглый жёлудь, полез за грибом и вытряхнул {delta} из шапки!"
    },
    {
      "id": "forest.ru.0309",
      "text": "🐿️ {user} точил палку для костра, решил передохнуть и нашёл {delta} в густой листве!"
    },
    {
      "id": "forest.ru.0310",
      "text": "🦉 {user} разводил костёр в овраге, обнял берёзу и стряхнул с ветки {delta} прямо на голову!"
    },
    {
      "id": "forest.ru.0311",
      "text": "🐿️ {user} переплетал лапти у пня, обнял берёзу и вытряхнул {delta} из шапки!"
    },
    {
      "id": "forest.ru.0312",
      "text": "🪵 {user} разводил костёр в овраге, перепутал тропу и обнаружил {delta} прямо в мхе!"
    },
    {
      "id": "forest.ru.0313",
      "text": "🐻 {user} точил палку для костра, повстречал ёжика и выкопал {delta} из-под коряги!"
    },
    {
      "id": "forest.ru.0314",
      "text": "🪵 {user} выпиливал свисток из ветки, решил передохнуть и вытряхнул {delta} из шапки!"
    },
    {
      "id": "forest.ru.0315",
      "text": "🐗 {user} наблюдал за белкой на сосне, подобрал странный камень и вытряхнул {delta} из шапки!"
    },
    {
      "id": "forest.ru.0316",
      "text": "🪶 {user} смотрел, как мох растёт, перепутал тропу и обнаружил {delta} прямо в мхе!"
    },
    {
      "id": "forest.ru.0317",
      "text": "🐺 {user} плёл венок из папоротника, вспомнил детство и вытряхнул {delta} из шапки!"
    },
    {
      "id": "forest.ru.0318",
      "text": "🐗 {user} переплетал лапти у пня, споткнулся о корни и случайно зацепил {delta} лаптём!"
    },
    {
      "id": "forest.ru.0319",
      "text": "🐺 {user} обходил поляну по периметру, подобрал странный камень и выкопал {delta} из-под коряги!"
    },
    {
      "id": "forest.ru.0320",
      "text": "🌲 {user} переобувался на привале, решил передохнуть и поднял {delta} с тропы!"
    },
    {
      "id": "forest.ru.0321",
      "text": "🐻 {user} рыл схрон под корягой, наткнулся на дупло и поднял {delta} с тропы!"
    },
    {
      "id": "forest.ru.0322",
      "text": "🌿 {user} пугал лису свистом, услышал хруст в кустах и стряхнул с ветки {delta} прямо на голову!"
    },
    {
      "id": "forest.ru.0323",
      "text": "🦡 {user} пел грустные песни ёлкам, наткнулся на дупло и обнаружил {delta} прямо в мхе!"
    },
    {
      "id": "forest.ru.0324",
      "text": "🐗 {user} плёл венок из папоротника, наткнулся на дупло и обнаружил {delta} прямо в мхе!"
    },
    {
      "id": "forest.ru.0325",
      "text": "🌲 {user} переплетал лапти у пня, вспомнил детство и выудил {delta} из дупла!"
    },
    {
      "id": "forest.ru.0326",
      "text": "🐺 {user} выпиливал свисток из ветки, обнял берёзу и получил {delta} в подарок от лешего!"
    },
    {
      "id": "forest.ru.0327",
      "text": "🪶 {user} переобувался на привале, перепутал тропу и обменял свой свисток на {delta} у филина!"
    },
    {
      "id": "forest.ru.0328",
      "text": "🪶 {user} продирался сквозь чащу, подобрал странный камень и услышал шёпот папоротника — и стал на {delta} длиннее!"
    },
    {
      "id": "forest.ru.0329",
      "text": "🌿 {user} разгребал муравейник палкой, вспомнил детство и получил {delta} в подарок от лешего!"
    },
    {
      "id": "forest.ru.0330",
      "text": "🪵 {user} наблюдал за белкой на сосне, перепутал тропу и получил {delta} в подарок от лешего!"
    },
    {
      "id": "forest.ru.0331",
      "text": "🐿️ {user} искал самый круглый жёлудь, вспомнил детство и вспомнил заветное слово — и тут же подрос на {delta}!"
    },
    {
      "id": "forest.ru.0332",
      "text": "🪶 {user} точил топор о валун, повстречал ёжика и нашёл {delta} в густой листве!"
    },
    {
      "id": "forest.ru.0333",
      "text": "🌳 {user} пугал лису свистом, решил передохнуть и выудил {delta} из дупла!"
    },
    {
      "id": "forest.ru.0334",
      "text": "🦉 {user} точил топор о валун, вспомнил детство и вытряхнул {delta} из шапки!"
    },
    {
      "id": "forest.ru.0335",
      "text": "🌳 {user} продирался сквозь чащу, выкопал кротовую нору и нашёл {delta} в густой листве!"
    },
    {
      "id": "forest.ru.0336",
      "text": "🐻 {user} точил топор о валун, выкопал кротовую нору и вытряхнул {delta} из шапки!"
    },
    {
      "id": "forest.ru.0337",
      "text": "🐗 {user} точил палку для костра, подобрал странный камень и вытряхнул {delta} из шапки!"
    },
    {
      "id": "forest.ru.0338",
      "text": "🐺 {user} точил топор о валун, споткнулся о корни и выкопал {delta} из-под коряги!"
    },
    {
      "id": "forest.ru.0339",
      "text": "🌲 {user} смотрел, как мох растёт, наткнулся на дупло и намерил {delta} у самого пня!"
    },
    {
      "id": "forest.ru.0340",
      "text": "🦌 {user} точил топор о валун, повстречал ёжика и выудил {delta} из дупла!"
    },
    {
      "id": "forest.ru.0341",
      "text": "🦌 {user} слушал кукушку у ручья, подобрал странный камень и услышал шёпот папоротника — и стал на {delta} длиннее!"
    },
    {
      "id": "forest.ru.0342",
      "text": "🐻 {user} выпиливал свисток из ветки, полез за грибом и увидел {delta} в траве и обрадовался!"
    },
    {
      "id": "forest.ru.0343",
      "text": "🍂 {user} плёл венок из папоротника, распугал бабочек и стряхнул с ветки {delta} прямо на голову!"
    },
    {
      "id": "forest.ru.0344",
      "text": "🍂 {user} плёл венок из папоротника, распугал бабочек и вытряхнул {delta} из шапки!"
    },
    {
      "id": "forest.ru.0345",
      "text": "🪶 {user} смотрел, как мох растёт, споткнулся о корни и выторговал {delta} у лесного духа!"
    },
    {
      "id": "forest.ru.0346",
      "text": "🌿 {user} ловил эхо у скалы, повстречал ёжика и поднял {delta} с тропы!"
    },
    {
      "id": "forest.ru.0347",
      "text": "🍄 {user} обходил поляну по периметру, наткнулся на дупло и получил {delta} в подарок от лешего!"
    },
    {
      "id": "forest.ru.0348",
      "text": "🪶 {user} смотрел, как мох растёт, подобрал странный камень и увидел {delta} в траве и обрадовался!"
    },
    {
      "id": "forest.ru.0349",
      "text": "🌳 {user} пел грустные песни ёлкам, споткнулся о корни и выторговал {delta} у лесного духа!"
    },
    {
      "id": "forest.ru.0350",
      "text": "🦡 {user} смотрел, как мох растёт, распугал бабочек и вытряхнул {delta} из шапки!"
    }
  ]
}
